[
    {
        "stepId": "STEP190",
        "stepName": "Url: WebTours",
        "infFile": "t1.inf",
        "time": 1600616861605
    },
    {
        "stepId": "STEP191",
        "stepName": "Submit Data: login.pl",
        "infFile": "t2.inf",
        "time": 1600616862103
    },
    {
        "stepId": "STEP192",
        "stepName": "Url: Search Flights Button",
        "infFile": "t3.inf",
        "time": 1600616862486
    },
    {
        "stepId": "STEP193",
        "stepName": "Submit Data: reservations.pl",
        "infFile": "t6.inf",
        "time": 1600616862891
    },
    {
        "stepId": "STEP194",
        "stepName": "Submit Data: reservations.pl_2",
        "infFile": "t7.inf",
        "time": 1600616863213
    },
    {
        "stepId": "STEP195",
        "stepName": "Submit Data: reservations.pl_3",
        "infFile": "t8.inf",
        "time": 1600616863551
    },
    {
        "stepId": "STEP196",
        "stepName": "Url: SignOff Button",
        "infFile": "t9.inf",
        "time": 1600616863896
    }
]